{
  "name": "images/Ringfrodo.webp",
  "bucket": "alexa-semijoias.appspot.com",
  "metageneration": 1,
  "generation": 1726681921922,
  "contentType": "image/webp",
  "storageClass": "STANDARD",
  "contentDisposition": "inline",
  "downloadTokens": [
    "ec7ea433-93e8-4bce-a869-e18eec71f921"
  ],
  "etag": "yduRRKuFyTNNREVpdNmx/rB6t3g",
  "customMetadata": {},
  "timeCreated": "2024-09-18T17:52:01.922Z",
  "updated": "2024-09-18T17:52:01.922Z",
  "size": 9566,
  "md5Hash": "KFFO26R3aaCXYtp43QleJw==",
  "crc32c": "1186991672"
}