{
  "name": "images/Takoyaki_8.webp",
  "bucket": "alexa-semijoias.appspot.com",
  "metageneration": 1,
  "generation": 1729709740732,
  "contentType": "image/webp",
  "storageClass": "STANDARD",
  "contentDisposition": "inline",
  "downloadTokens": [
    "264cc6ff-37ad-4f72-9149-b48728baccdd"
  ],
  "etag": "LCZ01ocomjPeQ7uhdvUpinJfbr8",
  "customMetadata": {},
  "timeCreated": "2024-10-23T18:55:40.732Z",
  "updated": "2024-10-23T18:55:40.732Z",
  "size": 15754,
  "md5Hash": "5lfWPcbbudX40eXV06uBrQ==",
  "crc32c": "2391286814"
}